AUTHOR.txt
CHANGES.txt
LICENSE.txt
MANIFEST.in
README.txt
bootstrap.py
buildout.cfg
setup.cfg
setup.py
version.txt
src/rod/__init__.py
src/rod.recipe.appengine.egg-info/PKG-INFO
src/rod.recipe.appengine.egg-info/SOURCES.txt
src/rod.recipe.appengine.egg-info/dependency_links.txt
src/rod.recipe.appengine.egg-info/entry_points.txt
src/rod.recipe.appengine.egg-info/namespace_packages.txt
src/rod.recipe.appengine.egg-info/not-zip-safe
src/rod.recipe.appengine.egg-info/requires.txt
src/rod.recipe.appengine.egg-info/top_level.txt
src/rod/recipe/__init__.py
src/rod/recipe/appengine/README.txt
src/rod/recipe/appengine/__init__.py
src/rod/recipe/appengine/tests/__init__.py
src/rod/recipe/appengine/tests/patch.diff
src/rod/recipe/appengine/tests/test_doc.py
src/rod/recipe/appengine/tests/bazpkg/README.txt
src/rod/recipe/appengine/tests/bazpkg/setup.py
src/rod/recipe/appengine/tests/foo.bar/README.txt
src/rod/recipe/appengine/tests/foo.bar/setup.py