Metadata-Version: 1.1
Name: rod.recipe.appengine
Version: 2.0.2
Summary: ZC Buildout recipe for setting up a Google App Engine development environment.
Home-page: http://code.google.com/p/rodrecipes
Author: Tobias Rodaebel
Author-email: tobias.rodaebel@googlemail.com
License: LGPL 3
Keywords: appengine gae zc.buildout recipe zope
Platform: UNKNOWN
Classifier: Development Status :: 5 - Production/Stable
Classifier: Framework :: Buildout
Classifier: Intended Audience :: Developers
Classifier: License :: OSI Approved :: GNU Library or Lesser General Public License (LGPL)
Classifier: Topic :: Software Development :: Build Tools
Classifier: Topic :: Software Development :: Libraries :: Python Modules
